opentrace/__init__.py
opentrace/client.py
opentrace-1.2.8.dist-info/METADATA
opentrace-1.2.8.dist-info/WHEEL
opentrace-1.2.8.dist-info/RECORD
