Metadata-Version: 2.4
Name: opentrace
Version: 1.2.8
Summary: Official Python SDK for OpenTrace Analytics (https://github.com/del4pp/opentrace)
Project-URL: Homepage, https://opentrace.dev
Project-URL: Repository, https://github.com/del4pp/opentrace
Project-URL: Bug Tracker, https://github.com/del4pp/opentrace/issues
Author-email: del4pp <del4pp.dev@proton.me>
Classifier: License :: OSI Approved :: MIT License
Classifier: Operating System :: OS Independent
Classifier: Programming Language :: Python :: 3
Requires-Python: >=3.7
Requires-Dist: requests>=2.25.0
